sonicos_api/__init__.py
sonicos_api/sonicOS.py
sonicos_api-0.1.7.dist-info/WHEEL
sonicos_api-0.1.7.dist-info/METADATA
sonicos_api-0.1.7.dist-info/RECORD
