Metadata-Version: 2.1
Name: sonicos-api
Version: 0.1.7
Summary: Lib to communicate with SonicWall's API
Author: joaovmlima
Author-email: oi.oaoj@gmail.com
Requires-Python: >=3.8,<4.0
Classifier: Programming Language :: Python :: 3
Classifier: Programming Language :: Python :: 3.8
Classifier: Programming Language :: Python :: 3.9
Requires-Dist: requests (>=2.26.0,<3.0.0)
